ULA.v
module ULA(a,b,op,result);

	input [3:0] a,b;
	input [1:0] op;
	output reg [3:0] result;

	parameter sum=0,sub=1,mult=2,div=3;	
	
	always @ (*) begin
		case(op) 
			sum: result <= a + b;
			sub: result <= a - b;
			mult: result <= a * b;
			div: result <= a/b;
			default: result <= 0;
		endcase
	end
endmodule

test_banch.v
`include "ULA.v"

module test_banch();

	reg [3:0] a,b;
	reg [1:0] op;
	wire [3:0] result;

	ULA ULA(
		.a(a),
		.b(b),
		.op(op),
		.result(result)
	);	
	
	initial begin	
		a <= 0;
		b <= 2;
		op <= 0; // Soma	
		$dumpfile("wave.vcd"); // Especifica o arquivo 
		$dumpvars; // Especifica pra colocar todos os sinais 
		#500;
		op <= 1;
		#500;
		op <= 2;
		#500;
		op <= 3;
		#1000  $finish; 
	end

	always begin		
		if(a < 15) a <= a + 1;
		else a <= 0;
		#10;		
	end
	
endmodule

wave.vcd
$date
	Mon May 21 15:29:14 2018
$end
$version
	Icarus Verilog
$end
$timescale
	1s
$end
$scope module test_banch $end
$var wire 4 ! result [3:0] $end
$var reg 4 " a [3:0] $end
$var reg 4 # b [3:0] $end
$var reg 2 $ op [1:0] $end
$scope module ULA $end
$var wire 4 % a [3:0] $end
$var wire 4 & b [3:0] $end
$var wire 2 ' op [1:0] $end
$var reg 4 ( result [3:0] $end
$upscope $end
$upscope $end
$enddefinitions $end
#0
$dumpvars
b10 (
b0 '
b10 &
b0 %
b0 $
b10 #
b0 "
b10 !
$end
#10
b11 !
b11 (
b1 "
b1 %
#20
b100 !
b100 (
b10 "
b10 %
#30
b101 !
b101 (
b11 "
b11 %
#40
b110 !
b110 (
b100 "
b100 %
#50
b111 !
b111 (
b101 "
b101 %
#60
b1000 !
b1000 (
b110 "
b110 %
#70
b1001 !
b1001 (
b111 "
b111 %
#80
b1010 !
b1010 (
b1000 "
b1000 %
#90
b1011 !
b1011 (
b1001 "
b1001 %
#100
b1100 !
b1100 (
b1010 "
b1010 %
#110
b1101 !
b1101 (
b1011 "
b1011 %
#120
b1110 !
b1110 (
b1100 "
b1100 %
#130
b1111 !
b1111 (
b1101 "
b1101 %
#140
b0 !
b0 (
b1110 "
b1110 %
#150
b1 !
b1 (
b1111 "
b1111 %
#160
b10 !
b10 (
b0 "
b0 %
#170
b11 !
b11 (
b1 "
b1 %
#180
b100 !
b100 (
b10 "
b10 %
#190
b101 !
b101 (
b11 "
b11 %
#200
b110 !
b110 (
b100 "
b100 %
#210
b111 !
b111 (
b101 "
b101 %
#220
b1000 !
b1000 (
b110 "
b110 %
#230
b1001 !
b1001 (
b111 "
b111 %
#240
b1010 !
b1010 (
b1000 "
b1000 %
#250
b1011 !
b1011 (
b1001 "
b1001 %
#260
b1100 !
b1100 (
b1010 "
b1010 %
#270
b1101 !
b1101 (
b1011 "
b1011 %
#280
b1110 !
b1110 (
b1100 "
b1100 %
#290
b1111 !
b1111 (
b1101 "
b1101 %
#300
b0 !
b0 (
b1110 "
b1110 %
#310
b1 !
b1 (
b1111 "
b1111 %
#320
b10 !
b10 (
b0 "
b0 %
#330
b11 !
b11 (
b1 "
b1 %
#340
b100 !
b100 (
b10 "
b10 %
#350
b101 !
b101 (
b11 "
b11 %
#360
b110 !
b110 (
b100 "
b100 %
#370
b111 !
b111 (
b101 "
b101 %
#380
b1000 !
b1000 (
b110 "
b110 %
#390
b1001 !
b1001 (
b111 "
b111 %
#400
b1010 !
b1010 (
b1000 "
b1000 %
#410
b1011 !
b1011 (
b1001 "
b1001 %
#420
b1100 !
b1100 (
b1010 "
b1010 %
#430
b1101 !
b1101 (
b1011 "
b1011 %
#440
b1110 !
b1110 (
b1100 "
b1100 %
#450
b1111 !
b1111 (
b1101 "
b1101 %
#460
b0 !
b0 (
b1110 "
b1110 %
#470
b1 !
b1 (
b1111 "
b1111 %
#480
b10 !
b10 (
b0 "
b0 %
#490
b11 !
b11 (
b1 "
b1 %
#500
b0 !
b0 (
b10 "
b10 %
b1 $
b1 '
#510
b1 !
b1 (
b11 "
b11 %
#520
b10 !
b10 (
b100 "
b100 %
#530
b11 !
b11 (
b101 "
b101 %
#540
b100 !
b100 (
b110 "
b110 %
#550
b101 !
b101 (
b111 "
b111 %
#560
b110 !
b110 (
b1000 "
b1000 %
#570
b111 !
b111 (
b1001 "
b1001 %
#580
b1000 !
b1000 (
b1010 "
b1010 %
#590
b1001 !
b1001 (
b1011 "
b1011 %
#600
b1010 !
b1010 (
b1100 "
b1100 %
#610
b1011 !
b1011 (
b1101 "
b1101 %
#620
b1100 !
b1100 (
b1110 "
b1110 %
#630
b1101 !
b1101 (
b1111 "
b1111 %
#640
b1110 !
b1110 (
b0 "
b0 %
#650
b1111 !
b1111 (
b1 "
b1 %
#660
b0 !
b0 (
b10 "
b10 %
#670
b1 !
b1 (
b11 "
b11 %
#680
b10 !
b10 (
b100 "
b100 %
#690
b11 !
b11 (
b101 "
b101 %
#700
b100 !
b100 (
b110 "
b110 %
#710
b101 !
b101 (
b111 "
b111 %
#720
b110 !
b110 (
b1000 "
b1000 %
#730
b111 !
b111 (
b1001 "
b1001 %
#740
b1000 !
b1000 (
b1010 "
b1010 %
#750
b1001 !
b1001 (
b1011 "
b1011 %
#760
b1010 !
b1010 (
b1100 "
b1100 %
#770
b1011 !
b1011 (
b1101 "
b1101 %
#780
b1100 !
b1100 (
b1110 "
b1110 %
#790
b1101 !
b1101 (
b1111 "
b1111 %
#800
b1110 !
b1110 (
b0 "
b0 %
#810
b1111 !
b1111 (
b1 "
b1 %
#820
b0 !
b0 (
b10 "
b10 %
#830
b1 !
b1 (
b11 "
b11 %
#840
b10 !
b10 (
b100 "
b100 %
#850
b11 !
b11 (
b101 "
b101 %
#860
b100 !
b100 (
b110 "
b110 %
#870
b101 !
b101 (
b111 "
b111 %
#880
b110 !
b110 (
b1000 "
b1000 %
#890
b111 !
b111 (
b1001 "
b1001 %
#900
b1000 !
b1000 (
b1010 "
b1010 %
#910
b1001 !
b1001 (
b1011 "
b1011 %
#920
b1010 !
b1010 (
b1100 "
b1100 %
#930
b1011 !
b1011 (
b1101 "
b1101 %
#940
b1100 !
b1100 (
b1110 "
b1110 %
#950
b1101 !
b1101 (
b1111 "
b1111 %
#960
b1110 !
b1110 (
b0 "
b0 %
#970
b1111 !
b1111 (
b1 "
b1 %
#980
b0 !
b0 (
b10 "
b10 %
#990
b1 !
b1 (
b11 "
b11 %
#1000
b1000 !
b1000 (
b100 "
b100 %
b10 $
b10 '
#1010
b1010 !
b1010 (
b101 "
b101 %
#1020
b1100 !
b1100 (
b110 "
b110 %
#1030
b1110 !
b1110 (
b111 "
b111 %
#1040
b0 !
b0 (
b1000 "
b1000 %
#1050
b10 !
b10 (
b1001 "
b1001 %
#1060
b100 !
b100 (
b1010 "
b1010 %
#1070
b110 !
b110 (
b1011 "
b1011 %
#1080
b1000 !
b1000 (
b1100 "
b1100 %
#1090
b1010 !
b1010 (
b1101 "
b1101 %
#1100
b1100 !
b1100 (
b1110 "
b1110 %
#1110
b1110 !
b1110 (
b1111 "
b1111 %
#1120
b0 !
b0 (
b0 "
b0 %
#1130
b10 !
b10 (
b1 "
b1 %
#1140
b100 !
b100 (
b10 "
b10 %
#1150
b110 !
b110 (
b11 "
b11 %
#1160
b1000 !
b1000 (
b100 "
b100 %
#1170
b1010 !
b1010 (
b101 "
b101 %
#1180
b1100 !
b1100 (
b110 "
b110 %
#1190
b1110 !
b1110 (
b111 "
b111 %
#1200
b0 !
b0 (
b1000 "
b1000 %
#1210
b10 !
b10 (
b1001 "
b1001 %
#1220
b100 !
b100 (
b1010 "
b1010 %
#1230
b110 !
b110 (
b1011 "
b1011 %
#1240
b1000 !
b1000 (
b1100 "
b1100 %
#1250
b1010 !
b1010 (
b1101 "
b1101 %
#1260
b1100 !
b1100 (
b1110 "
b1110 %
#1270
b1110 !
b1110 (
b1111 "
b1111 %
#1280
b0 !
b0 (
b0 "
b0 %
#1290
b10 !
b10 (
b1 "
b1 %
#1300
b100 !
b100 (
b10 "
b10 %
#1310
b110 !
b110 (
b11 "
b11 %
#1320
b1000 !
b1000 (
b100 "
b100 %
#1330
b1010 !
b1010 (
b101 "
b101 %
#1340
b1100 !
b1100 (
b110 "
b110 %
#1350
b1110 !
b1110 (
b111 "
b111 %
#1360
b0 !
b0 (
b1000 "
b1000 %
#1370
b10 !
b10 (
b1001 "
b1001 %
#1380
b100 !
b100 (
b1010 "
b1010 %
#1390
b110 !
b110 (
b1011 "
b1011 %
#1400
b1000 !
b1000 (
b1100 "
b1100 %
#1410
b1010 !
b1010 (
b1101 "
b1101 %
#1420
b1100 !
b1100 (
b1110 "
b1110 %
#1430
b1110 !
b1110 (
b1111 "
b1111 %
#1440
b0 !
b0 (
b0 "
b0 %
#1450
b10 !
b10 (
b1 "
b1 %
#1460
b100 !
b100 (
b10 "
b10 %
#1470
b110 !
b110 (
b11 "
b11 %
#1480
b1000 !
b1000 (
b100 "
b100 %
#1490
b1010 !
b1010 (
b101 "
b101 %
#1500
b11 !
b11 (
b110 "
b110 %
b11 $
b11 '
#1510
b111 "
b111 %
#1520
b100 !
b100 (
b1000 "
b1000 %
#1530
b1001 "
b1001 %
#1540
b101 !
b101 (
b1010 "
b1010 %
#1550
b1011 "
b1011 %
#1560
b110 !
b110 (
b1100 "
b1100 %
#1570
b1101 "
b1101 %
#1580
b111 !
b111 (
b1110 "
b1110 %
#1590
b1111 "
b1111 %
#1600
b0 !
b0 (
b0 "
b0 %
#1610
b1 "
b1 %
#1620
b1 !
b1 (
b10 "
b10 %
#1630
b11 "
b11 %
#1640
b10 !
b10 (
b100 "
b100 %
#1650
b101 "
b101 %
#1660
b11 !
b11 (
b110 "
b110 %
#1670
b111 "
b111 %
#1680
b100 !
b100 (
b1000 "
b1000 %
#1690
b1001 "
b1001 %
#1700
b101 !
b101 (
b1010 "
b1010 %
#1710
b1011 "
b1011 %
#1720
b110 !
b110 (
b1100 "
b1100 %
#1730
b1101 "
b1101 %
#1740
b111 !
b111 (
b1110 "
b1110 %
#1750
b1111 "
b1111 %
#1760
b0 !
b0 (
b0 "
b0 %
#1770
b1 "
b1 %
#1780
b1 !
b1 (
b10 "
b10 %
#1790
b11 "
b11 %
#1800
b10 !
b10 (
b100 "
b100 %
#1810
b101 "
b101 %
#1820
b11 !
b11 (
b110 "
b110 %
#1830
b111 "
b111 %
#1840
b100 !
b100 (
b1000 "
b1000 %
#1850
b1001 "
b1001 %
#1860
b101 !
b101 (
b1010 "
b1010 %
#1870
b1011 "
b1011 %
#1880
b110 !
b110 (
b1100 "
b1100 %
#1890
b1101 "
b1101 %
#1900
b111 !
b111 (
b1110 "
b1110 %
#1910
b1111 "
b1111 %
#1920
b0 !
b0 (
b0 "
b0 %
#1930
b1 "
b1 %
#1940
b1 !
b1 (
b10 "
b10 %
#1950
b11 "
b11 %
#1960
b10 !
b10 (
b100 "
b100 %
#1970
b101 "
b101 %
#1980
b11 !
b11 (
b110 "
b110 %
#1990
b111 "
b111 %
#2000
b100 !
b100 (
b1000 "
b1000 %
#2010
b1001 "
b1001 %
#2020
b101 !
b101 (
b1010 "
b1010 %
#2030
b1011 "
b1011 %
#2040
b110 !
b110 (
b1100 "
b1100 %
#2050
b1101 "
b1101 %
#2060
b111 !
b111 (
b1110 "
b1110 %
#2070
b1111 "
b1111 %
#2080
b0 !
b0 (
b0 "
b0 %
#2090
b1 "
b1 %
#2100
b1 !
b1 (
b10 "
b10 %
#2110
b11 "
b11 %
#2120
b10 !
b10 (
b100 "
b100 %
#2130
b101 "
b101 %
#2140
b11 !
b11 (
b110 "
b110 %
#2150
b111 "
b111 %
#2160
b100 !
b100 (
b1000 "
b1000 %
#2170
b1001 "
b1001 %
#2180
b101 !
b101 (
b1010 "
b1010 %
#2190
b1011 "
b1011 %
#2200
b110 !
b110 (
b1100 "
b1100 %
#2210
b1101 "
b1101 %
#2220
b111 !
b111 (
b1110 "
b1110 %
#2230
b1111 "
b1111 %
#2240
b0 !
b0 (
b0 "
b0 %
#2250
b1 "
b1 %
#2260
b1 !
b1 (
b10 "
b10 %
#2270
b11 "
b11 %
#2280
b10 !
b10 (
b100 "
b100 %
#2290
b101 "
b101 %
#2300
b11 !
b11 (
b110 "
b110 %
#2310
b111 "
b111 %
#2320
b100 !
b100 (
b1000 "
b1000 %
#2330
b1001 "
b1001 %
#2340
b101 !
b101 (
b1010 "
b1010 %
#2350
b1011 "
b1011 %
#2360
b110 !
b110 (
b1100 "
b1100 %
#2370
b1101 "
b1101 %
#2380
b111 !
b111 (
b1110 "
b1110 %
#2390
b1111 "
b1111 %
#2400
b0 !
b0 (
b0 "
b0 %
#2410
b1 "
b1 %
#2420
b1 !
b1 (
b10 "
b10 %
#2430
b11 "
b11 %
#2440
b10 !
b10 (
b100 "
b100 %
#2450
b101 "
b101 %
#2460
b11 !
b11 (
b110 "
b110 %
#2470
b111 "
b111 %
#2480
b100 !
b100 (
b1000 "
b1000 %
#2490
b1001 "
b1001 %
#2500
b101 !
b101 (
b1010 "
b1010 %
